[
    {
        "key": "dbln",
        "value": "%7B%2261575495128014%22%3A%22Y4fiyRSM%22%7D",
        "domain": "facebook.com",
        "path": "/login/device-based/",
        "hostOnly": false,
        "creation": "2025-04-25T06:35:40.541Z",
        "lastAccessed": "2025-04-25T06:35:40.542Z"
    },
    {
        "key": "datr",
        "value": "vzD8ZxThUxiwMuJWJ282Q5Y9",
        "domain": "facebook.com",
        "path": "/",
        "hostOnly": false,
        "creation": "2025-04-25T06:35:40.543Z",
        "lastAccessed": "2025-04-25T06:35:40.543Z"
    },
    {
        "key": "sb",
        "value": "vzD8Z6QF711zU8m1wsvzeP3F",
        "domain": "facebook.com",
        "path": "/",
        "hostOnly": false,
        "creation": "2025-04-25T06:35:40.543Z",
        "lastAccessed": "2025-04-25T06:35:40.543Z"
    },
    {
        "key": "ps_l",
        "value": "1",
        "domain": "facebook.com",
        "path": "/",
        "hostOnly": false,
        "creation": "2025-04-25T06:35:40.543Z",
        "lastAccessed": "2025-04-25T06:35:40.543Z"
    },
    {
        "key": "ps_n",
        "value": "1",
        "domain": "facebook.com",
        "path": "/",
        "hostOnly": false,
        "creation": "2025-04-25T06:35:40.543Z",
        "lastAccessed": "2025-04-25T06:35:40.543Z"
    },
    {
        "key": "locale",
        "value": "ar_AR",
        "domain": "facebook.com",
        "path": "/",
        "hostOnly": false,
        "creation": "2025-04-25T06:35:40.543Z",
        "lastAccessed": "2025-04-25T06:35:40.543Z"
    },
    {
        "key": "wd",
        "value": "320x623",
        "domain": "facebook.com",
        "path": "/",
        "hostOnly": false,
        "creation": "2025-04-25T06:35:40.543Z",
        "lastAccessed": "2025-04-25T06:35:40.543Z"
    },
    {
        "key": "c_user",
        "value": "61575495128014",
        "domain": "facebook.com",
        "path": "/",
        "hostOnly": false,
        "creation": "2025-04-25T06:35:40.543Z",
        "lastAccessed": "2025-04-25T06:35:40.543Z"
    },
    {
        "key": "fr",
        "value": "0oHQT5HJg8z8fKtbu.AWf06fDAigrP-2Dk_erooIvGPUNrK6lWDRzTLlx9crZ0tPxKijE.BoCynB..AAA.0.0.BoCyo-.AWebmfNlQM5Sqz0qnJAG5bqV4qk",
        "domain": "facebook.com",
        "path": "/",
        "hostOnly": false,
        "creation": "2025-04-25T06:35:40.543Z",
        "lastAccessed": "2025-04-25T06:35:40.543Z"
    },
    {
        "key": "xs",
        "value": "30%3AmqR-WVK5nyPOrQ%3A2%3A1745562176%3A-1%3A-1",
        "domain": "facebook.com",
        "path": "/",
        "hostOnly": false,
        "creation": "2025-04-25T06:35:40.543Z",
        "lastAccessed": "2025-04-25T06:35:40.543Z"
    },
    {
        "key": "vpd",
        "value": "v1%3B623x320x2.25",
        "domain": "facebook.com",
        "path": "/",
        "hostOnly": false,
        "creation": "2025-04-25T06:35:40.543Z",
        "lastAccessed": "2025-04-25T06:35:40.543Z"
    },
    {
        "key": "fbl_st",
        "value": "101037209%3BT%3A29092713",
        "domain": "facebook.com",
        "path": "/",
        "hostOnly": false,
        "creation": "2025-04-25T06:35:40.543Z",
        "lastAccessed": "2025-04-25T06:35:40.543Z"
    },
    {
        "key": "wl_cbv",
        "value": "v2%3Bclient_version%3A2795%3Btimestamp%3A1745562778",
        "domain": "facebook.com",
        "path": "/",
        "hostOnly": false,
        "creation": "2025-04-25T06:35:40.543Z",
        "lastAccessed": "2025-04-25T06:35:40.543Z"
    }
        ]
